{
  "playlist_name": "Sáng TV",
  "last_updated": "00:02 10/05/2026",
  "buncha": [
    {
      "title": "Dinamo Zagreb vs Hajduk Split",
      "trang_thai": "Đã kết thúc 🏁",
      "is_live": false,
      "thoi_gian": "21:00 09/05/2026",
      "logo_nha": "https://ui-avatars.com/api/?name=Di&size=200&background=1565C0&color=ffffff&bold=true",
      "link_xem": "https://bunchatv4.net/truc-tiep/dinamo-zagreb-vs-hajduk-split-2100-09-05-2026/601446475",
      "stream_url": "https://example.com/waiting.mp4"
    },
    {
      "title": "Podhale Nowy Targ vs Chojniczanka Chojnice",
      "trang_thai": "Đã kết thúc 🏁",
      "is_live": false,
      "thoi_gian": "21:00 09/05/2026",
      "logo_nha": "https://ui-avatars.com/api/?name=Po&size=200&background=1565C0&color=ffffff&bold=true",
      "link_xem": "https://bunchatv4.net/truc-tiep/podhale-nowy-targ-vs-chojniczanka-chojnice-2100-09-05-2026/601446478",
      "stream_url": "https://example.com/waiting.mp4"
    },
    {
      "title": "Hsc Hannover vs Hannover 96 Am",
      "trang_thai": "Đã kết thúc 🏁",
      "is_live": false,
      "thoi_gian": "21:00 09/05/2026",
      "logo_nha": "https://ui-avatars.com/api/?name=Hs&size=200&background=1565C0&color=ffffff&bold=true",
      "link_xem": "https://bunchatv4.net/truc-tiep/hsc-hannover-vs-hannover-96-am-2100-09-05-2026/601446523",
      "stream_url": "https://example.com/waiting.mp4"
    },
    {
      "title": "Vaasa Vps vs Gnistan Helsinki",
      "trang_thai": "Đã kết thúc 🏁",
      "is_live": false,
      "thoi_gian": "21:00 09/05/2026",
      "logo_nha": "https://ui-avatars.com/api/?name=Va&size=200&background=1565C0&color=ffffff&bold=true",
      "link_xem": "https://bunchatv4.net/truc-tiep/vaasa-vps-vs-gnistan-helsinki-2100-09-05-2026/601446562",
      "stream_url": "https://example.com/waiting.mp4"
    },
    {
      "title": "Eskilsminne If vs Utsiktens Bk",
      "trang_thai": "Đã kết thúc 🏁",
      "is_live": false,
      "thoi_gian": "21:00 09/05/2026",
      "logo_nha": "https://ui-avatars.com/api/?name=Es&size=200&background=1565C0&color=ffffff&bold=true",
      "link_xem": "https://bunchatv4.net/truc-tiep/eskilsminne-if-vs-utsiktens-bk-2100-09-05-2026/601446565",
      "stream_url": "https://example.com/waiting.mp4"
    },
    {
      "title": "Fc Rosengard vs Tvaakers If",
      "trang_thai": "Đã kết thúc 🏁",
      "is_live": false,
      "thoi_gian": "21:00 09/05/2026",
      "logo_nha": "https://ui-avatars.com/api/?name=Fc&size=200&background=1565C0&color=ffffff&bold=true",
      "link_xem": "https://bunchatv4.net/truc-tiep/fc-rosengard-vs-tvaakers-if-2100-09-05-2026/601446568",
      "stream_url": "https://example.com/waiting.mp4"
    },
    {
      "title": "Skovde Aik vs Angelholms Ff",
      "trang_thai": "Đã kết thúc 🏁",
      "is_live": false,
      "thoi_gian": "21:00 09/05/2026",
      "logo_nha": "https://ui-avatars.com/api/?name=Sk&size=200&background=1565C0&color=ffffff&bold=true",
      "link_xem": "https://bunchatv4.net/truc-tiep/skovde-aik-vs-angelholms-ff-2100-09-05-2026/601446571",
      "stream_url": "https://example.com/waiting.mp4"
    },
    {
      "title": "Fc Trollhattan vs Lunds Bk",
      "trang_thai": "Đã kết thúc 🏁",
      "is_live": false,
      "thoi_gian": "21:00 09/05/2026",
      "logo_nha": "https://ui-avatars.com/api/?name=Fc&size=200&background=1565C0&color=ffffff&bold=true",
      "link_xem": "https://bunchatv4.net/truc-tiep/fc-trollhattan-vs-lunds-bk-2100-09-05-2026/601446574",
      "stream_url": "https://example.com/waiting.mp4"
    },
    {
      "title": "Fbk Karlstad vs Jarfalla",
      "trang_thai": "Đã kết thúc 🏁",
      "is_live": false,
      "thoi_gian": "21:00 09/05/2026",
      "logo_nha": "https://ui-avatars.com/api/?name=Fb&size=200&background=1565C0&color=ffffff&bold=true",
      "link_xem": "https://bunchatv4.net/truc-tiep/fbk-karlstad-vs-jarfalla-2100-09-05-2026/601446577",
      "stream_url": "https://example.com/waiting.mp4"
    },
    {
      "title": "Hammarby Tff vs Assyriska",
      "trang_thai": "Đã kết thúc 🏁",
      "is_live": false,
      "thoi_gian": "21:00 09/05/2026",
      "logo_nha": "https://ui-avatars.com/api/?name=Ha&size=200&background=1565C0&color=ffffff&bold=true",
      "link_xem": "https://bunchatv4.net/truc-tiep/hammarby-tff-vs-assyriska-2100-09-05-2026/601446580",
      "stream_url": "https://example.com/waiting.mp4"
    },
    {
      "title": "Karlbergs Bk vs If Karlstad Fotboll",
      "trang_thai": "Đã kết thúc 🏁",
      "is_live": false,
      "thoi_gian": "21:00 09/05/2026",
      "logo_nha": "https://ui-avatars.com/api/?name=Ka&size=200&background=1565C0&color=ffffff&bold=true",
      "link_xem": "https://bunchatv4.net/truc-tiep/karlbergs-bk-vs-if-karlstad-fotboll-2100-09-05-2026/601446583",
      "stream_url": "https://example.com/waiting.mp4"
    },
    {
      "title": "Ifk Stocksund vs Fc Stockholm Internazionale",
      "trang_thai": "Đã kết thúc 🏁",
      "is_live": false,
      "thoi_gian": "21:00 09/05/2026",
      "logo_nha": "https://ui-avatars.com/api/?name=If&size=200&background=1565C0&color=ffffff&bold=true",
      "link_xem": "https://bunchatv4.net/truc-tiep/ifk-stocksund-vs-fc-stockholm-internazionale-2100-09-05-2026/601446586",
      "stream_url": "https://example.com/waiting.mp4"
    }
  ],
  "hoiquan": [
    {
      "title": "Lazio vs Inter.Fp5Irwz0Iv",
      "trang_thai": "Sắp diễn ra ⏳",
      "is_live": false,
      "thoi_gian": "Unknown",
      "logo_nha": "https://ui-avatars.com/api/?name=La&size=200&background=1565C0&color=ffffff&bold=true",
      "link_xem": "https://sv2.hoiquan3.live/truc-tiep/bong-da/serie-a-1758631315616/lazio-vs-inter.fp5irwz0iv/7246",
      "stream_url": "https://example.com/waiting.mp4"
    },
    {
      "title": "Manchester City vs Brentford.Dnsy Kleos",
      "trang_thai": "Sắp diễn ra ⏳",
      "is_live": false,
      "thoi_gian": "Unknown",
      "logo_nha": "https://ui-avatars.com/api/?name=Ma&size=200&background=1565C0&color=ffffff&bold=true",
      "link_xem": "https://sv2.hoiquan3.live/truc-tiep/bong-da/premier-league-1758631271470/manchester-city-vs-brentford.DNSy-KlEoS/7247",
      "stream_url": "https://example.com/waiting.mp4"
    },
    {
      "title": "Manchester City vs Brentford.Kulujduhru",
      "trang_thai": "Sắp diễn ra ⏳",
      "is_live": false,
      "thoi_gian": "Unknown",
      "logo_nha": "https://ui-avatars.com/api/?name=Ma&size=200&background=1565C0&color=ffffff&bold=true",
      "link_xem": "https://sv2.hoiquan3.live/truc-tiep/bong-da/premier-league-1758631271470/manchester-city-vs-brentford.KulujdUHru/7248",
      "stream_url": "https://example.com/waiting.mp4"
    },
    {
      "title": "Atletico Madrid vs Celta Vigo.Psmzvh4O04",
      "trang_thai": "Sắp diễn ra ⏳",
      "is_live": false,
      "thoi_gian": "Unknown",
      "logo_nha": "https://ui-avatars.com/api/?name=At&size=200&background=1565C0&color=ffffff&bold=true",
      "link_xem": "https://sv2.hoiquan3.live/truc-tiep/bong-da/la-liga.zb65Otf_xU/atletico-madrid-vs-celta-vigo.pSmzvH4o04/7249",
      "stream_url": "https://example.com/waiting.mp4"
    },
    {
      "title": "Vfl Wolfsburg vs Bayern Munchen.Dlc7R9Am1H",
      "trang_thai": "Sắp diễn ra ⏳",
      "is_live": false,
      "thoi_gian": "Unknown",
      "logo_nha": "https://ui-avatars.com/api/?name=Vf&size=200&background=1565C0&color=ffffff&bold=true",
      "link_xem": "https://sv2.hoiquan3.live/truc-tiep/bong-da/bundesliga-1758631341946/vfl-wolfsburg-vs-bayern-munchen.Dlc7r9AM1h/7250",
      "stream_url": "https://example.com/waiting.mp4"
    },
    {
      "title": "Toronto Fc vs Inter Miami.Iuoekzasos",
      "trang_thai": "Sắp diễn ra ⏳",
      "is_live": false,
      "thoi_gian": "Unknown",
      "logo_nha": "https://ui-avatars.com/api/?name=To&size=200&background=1565C0&color=ffffff&bold=true",
      "link_xem": "https://sv2.hoiquan3.live/truc-tiep/bong-da/major-league-soccer.DpvnnCwBbD/toronto-fc-vs-inter-miami.IuOeKZASoS/7287",
      "stream_url": "https://example.com/waiting.mp4"
    },
    {
      "title": "Lecce vs Juventus.00Lwdcqkrc",
      "trang_thai": "Sắp diễn ra ⏳",
      "is_live": false,
      "thoi_gian": "Unknown",
      "logo_nha": "https://ui-avatars.com/api/?name=Le&size=200&background=1565C0&color=ffffff&bold=true",
      "link_xem": "https://sv2.hoiquan3.live/truc-tiep/bong-da/serie-a-1758631315616/lecce-vs-juventus.00LwdcQkrc/7288",
      "stream_url": "https://example.com/waiting.mp4"
    },
    {
      "title": "Real Sociedad vs Real Betis.Sbtcutkp M",
      "trang_thai": "Sắp diễn ra ⏳",
      "is_live": false,
      "thoi_gian": "Unknown",
      "logo_nha": "https://ui-avatars.com/api/?name=Re&size=200&background=1565C0&color=ffffff&bold=true",
      "link_xem": "https://sv2.hoiquan3.live/truc-tiep/bong-da/la-liga.zb65Otf_xU/real-sociedad-vs-real-betis.SBtcUTKP-M/7289",
      "stream_url": "https://example.com/waiting.mp4"
    },
    {
      "title": "Nashville Sc vs Dc United.Gujhyyhibo",
      "trang_thai": "Sắp diễn ra ⏳",
      "is_live": false,
      "thoi_gian": "Unknown",
      "logo_nha": "https://ui-avatars.com/api/?name=Na&size=200&background=1565C0&color=ffffff&bold=true",
      "link_xem": "https://sv2.hoiquan3.live/truc-tiep/bong-da/major-league-soccer.DpvnnCwBbD/nashville-sc-vs-dc-united.gUjhYyhIBO/7302",
      "stream_url": "https://example.com/waiting.mp4"
    },
    {
      "title": "Yokohama F Marinos vs Kashima.Tqrtv18K9A",
      "trang_thai": "Sắp diễn ra ⏳",
      "is_live": false,
      "thoi_gian": "Unknown",
      "logo_nha": "https://ui-avatars.com/api/?name=Yo&size=200&background=1565C0&color=ffffff&bold=true",
      "link_xem": "https://sv2.hoiquan3.live/truc-tiep/bong-da/j1-league-1758631930094/yokohama-f-marinos-vs-kashima.tqrtV18K9a/7303",
      "stream_url": "https://example.com/waiting.mp4"
    },
    {
      "title": "Kashiwa Reysol vs Kawasaki Frontale.5Djjnvb_6W",
      "trang_thai": "Sắp diễn ra ⏳",
      "is_live": false,
      "thoi_gian": "Unknown",
      "logo_nha": "https://ui-avatars.com/api/?name=Ka&size=200&background=1565C0&color=ffffff&bold=true",
      "link_xem": "https://sv2.hoiquan3.live/truc-tiep/bong-da/j1-league-1758631930094/kashiwa-reysol-vs-kawasaki-frontale.5DJjNVB_6W/7305",
      "stream_url": "https://example.com/waiting.mp4"
    },
    {
      "title": "Jef United Chiba vs Machida Zelvia.Lhkxx_N5Nw",
      "trang_thai": "Sắp diễn ra ⏳",
      "is_live": false,
      "thoi_gian": "Unknown",
      "logo_nha": "https://ui-avatars.com/api/?name=Je&size=200&background=1565C0&color=ffffff&bold=true",
      "link_xem": "https://sv2.hoiquan3.live/truc-tiep/bong-da/j1-league-1758631930094/jef-united-chiba-vs-machida-zelvia.LHKxx_N5NW/7307",
      "stream_url": "https://example.com/waiting.mp4"
    }
  ]
}